LOLDeps/__init__.py
LOLDeps/dependency_checker.py
loldeps-0.0.4.dist-info/METADATA
loldeps-0.0.4.dist-info/WHEEL
loldeps-0.0.4.dist-info/entry_points.txt
loldeps-0.0.4.dist-info/licenses/LICENSE
loldeps-0.0.4.dist-info/RECORD
