Metadata-Version: 2.4
Name: LOLDeps
Version: 0.0.4
Summary: A tool to find vulnerabilities in packages using native package manager tools such as nuget.
Project-URL: Homepage, https://github.com/pritchyspritch/LOLDeps
Project-URL: Issues, https://github.com/pritchyspritch/LOLDeps/issues
Author-email: Sam Pritchard <47423802+pritchyspritch@users.noreply.github.com>
License-File: LICENSE
Classifier: License :: OSI Approved :: MIT License
Classifier: Operating System :: OS Independent
Classifier: Programming Language :: Python :: 3
Requires-Python: >=3.8
